selenium2/__init__.py
selenium2/browser.py
selenium2/browser.pyi
selenium2/config.py
selenium2/logger.py
selenium2/browser_support/__init__.py
selenium2/browser_support/_base.py
selenium2/browser_support/_driver.py
selenium2/browser_support/_webdrivercreator.py
selenium2/browser_support/alert.py
selenium2/browser_support/browsermanagement.py
selenium2/browser_support/cookies.py
selenium2/browser_support/element.py
selenium2/browser_support/frames.py
selenium2/browser_support/javascript.py
selenium2/browser_support/screenshot.py
selenium2/browser_support/selects.py
selenium2/browser_support/tables.py
selenium2/browser_support/testing.py
selenium2/browser_support/waiting.py
selenium2/browser_support/windowmanager.py
selenium2/site_specific/__init__.py
selenium2/site_specific/default.py
selenium2-0.1.1.dist-info/LICENSE
selenium2-0.1.1.dist-info/METADATA
selenium2-0.1.1.dist-info/WHEEL
selenium2-0.1.1.dist-info/top_level.txt
selenium2-0.1.1.dist-info/RECORD
