Metadata-Version: 2.1
Name: selenium2
Version: 0.1.1
Summary: A comprehensive Selenium wrapper designed to simplify browser automation and testing tasks.
Home-page: https://github.com/loudpumpkins/selenium2
Author: Alexei Panov
Author-email: alexei_panov@hotmail.com
License: MIT
Classifier: License :: OSI Approved :: Apache Software License
Classifier: Programming Language :: Python :: 3.8
Classifier: Operating System :: OS Independent
Requires-Python: >=3.8
License-File: LICENSE
Requires-Dist: selenium ==4.2.0
Requires-Dist: beautifulsoup4 ==4.12.3
Provides-Extra: dev
Requires-Dist: pytest >=7.0 ; extra == 'dev'
Requires-Dist: twine >=4.0.2 ; extra == 'dev'
